hogu/__init__.py
hogu/app.py
hogu-2024.2.1.dist-info/METADATA
hogu-2024.2.1.dist-info/WHEEL
hogu-2024.2.1.dist-info/RECORD
