Metadata-Version: 2.1
Name: hogu
Version: 2024.2.1
Summary: 
Author: Horia Filimonescu
Author-email: horia.filimonescu+github@gmail.com
Requires-Python: >=3.10,<4.0
Classifier: Programming Language :: Python :: 3
Classifier: Programming Language :: Python :: 3.10
Classifier: Programming Language :: Python :: 3.11
Classifier: Programming Language :: Python :: 3.12
Requires-Dist: flask (>=3.0.2,<4.0.0)
